roche_datachapter_lib/__domain__.py
roche_datachapter_lib/__init__.py
roche_datachapter_lib/data_transformer.py
roche_datachapter_lib/db_config.py
roche_datachapter_lib/google_services.py
roche_datachapter_lib/google_services_enums.py
roche_datachapter_lib/job_manager.py
roche_datachapter_lib/logger.py
roche_datachapter_lib/query_manager.py
roche_datachapter_lib/result_type.py
roche_datachapter_lib-0.0.4499.dist-info/METADATA
roche_datachapter_lib-0.0.4499.dist-info/WHEEL
roche_datachapter_lib-0.0.4499.dist-info/licenses/LICENSE
roche_datachapter_lib-0.0.4499.dist-info/RECORD
